AXI_ACE_COMB/axi4_read.v
module axi4_read_fsm (
    input         clk,
    input         rst_n,

    // AXI Read Address Channel
    input         arvalid,
    output reg    arready,
    input  [3:0]  arid,

    // AXI Read Data Channel
    output reg        rvalid,
    input             rready,
    output reg [31:0] rdata
);

    localparam IDLE = 2'b00;
    localparam R_S1 = 2'b01;
    localparam R_S2 = 2'b10;

    reg [1:0] state, next_state;
    reg [3:0] arid_latched;

    // Memory
    reg [31:0] mem [0:3];
    initial begin
        mem[0] = 32'hAAAA_1111;
        mem[1] = 32'hBBBB_2222;
        mem[2] = 32'hCCCC_3333;
        mem[3] = 32'hDDDD_4444;
    end

    // State register
    always @(posedge clk or negedge rst_n) begin
        if (!rst_n)
            state <= IDLE;
        else
            state <= next_state;
    end

    // Next-state logic (Fig.5 exact)
    always @(*) begin
        next_state = state;
        case (state)
            IDLE:
                if (arvalid)
                    next_state = R_S1;

            R_S1:
                if (rready)
                    next_state = R_S2;

            R_S2:
                next_state = IDLE;
        endcase
    end

    // Output + datapath (FIXED)
    always @(posedge clk or negedge rst_n) begin
        if (!rst_n) begin
            arready       <= 0;
            rvalid        <= 0;
            rdata         <= 0;
            arid_latched  <= 0;
        end else begin
            arready <= 0;
            rvalid  <= 0;

            case (state)

                // IDLE: accept address
                IDLE: begin
                    arready <= 1'b1;
                    if (arvalid)               // ✅ FIX
                        arid_latched <= arid;  // latch ID
                end

                // r_s1: drive read data (stable)
                R_S1: begin
                    rvalid <= 1'b1;
                     if (rready)
                         rdata <= mem[arid_latched];
                end

                // r_s2: response / cleanup
                R_S2: begin
                    // no signals
                end

            endcase
        end
    end

endmodule

axi4/axiread/tb_axi4_read.v
`timescale 1ns/1ps

module tb_axi4_read_fsm;

    reg         clk;
    reg         rst_n;

    reg         arvalid;
    wire        arready;
    reg  [3:0]  arid;

    wire        rvalid;
    reg         rready;
    wire [31:0] rdata;

    // DUT
    axi4_read_fsm dut (
        .clk     (clk),
        .rst_n   (rst_n),
        .arvalid (arvalid),
        .arready (arready),
        .arid    (arid),
        .rvalid  (rvalid),
        .rready  (rready),
        .rdata   (rdata)
    );

    // Clock
    always #5 clk = ~clk;

    initial begin
        // -------------------------
        // Init
        // -------------------------
        clk     = 0;
        rst_n   = 0;
        arvalid = 0;
        arid    = 0;
        rready  = 0;

        // -------------------------
        // Reset
        // -------------------------
        #20;
        rst_n = 1;

        // -------------------------
        // IDLE → r_s1 (Address handshake)
        // -------------------------
        @(posedge clk);
        arid    = 2;        // expect mem[2] = CCCC_3333
        arvalid = 1;

        // wait for proper handshake
        wait (arvalid && arready);
        @(posedge clk);
        arvalid = 0;

        $display("[%0t] Address handshake complete", $time);

        // -------------------------
        // r_s1 : Stall (NO rready)
        // -------------------------
        repeat (3) begin
            @(posedge clk);
            if (rvalid)
                $display("[%0t] rvalid=1, rready=0 → NO DATA TRANSFER (correct)", $time);
        end

        // -------------------------
        // r_s1 → r_s2 (Read handshake)
        // -------------------------
        @(posedge clk);
        rready = 1;

        // THIS is the only legal read
        wait (rvalid && rready);
        @(posedge clk);

        $display("[%0t] READ HANDSHAKE OCCURRED", $time);
        $display("[%0t] READ DATA = %h", $time, rdata);

        rready = 0;

        // -------------------------
        // r_s2 → IDLE
        // -------------------------
        repeat (2) @(posedge clk);

        if (arready)
            $display("[%0t] Returned to IDLE (FSM correct)", $time);

        #20;
        $finish;
    end

    // Waveform dump
    initial begin
        $dumpfile("axi4_read_fsm.vcd");
        $dumpvars(0, tb_axi4_read_fsm);
    end

endmodule

axi4/axiread/axi4_read_fsm.vcd
$date
	Fri Jan 30 09:23:04 2026
$end
$version
	Icarus Verilog
$end
$timescale
	1ps
$end
$scope module tb_axi4_read_fsm $end
$var wire 1 ! rvalid $end
$var wire 32 " rdata [31:0] $end
$var wire 1 # arready $end
$var reg 4 $ arid [3:0] $end
$var reg 1 % arvalid $end
$var reg 1 & clk $end
$var reg 1 ' rready $end
$var reg 1 ( rst_n $end
$scope module dut $end
$var wire 4 ) arid [3:0] $end
$var wire 1 % arvalid $end
$var wire 1 & clk $end
$var wire 1 ' rready $end
$var wire 1 ( rst_n $end
$var reg 4 * arid_latched [3:0] $end
$var reg 1 # arready $end
$var reg 2 + next_state [1:0] $end
$var reg 32 , rdata [31:0] $end
$var reg 1 ! rvalid $end
$var reg 2 - state [1:0] $end
$upscope $end
$upscope $end
$enddefinitions $end
#0
$dumpvars
b0 -
b0 ,
b0 +
b0 *
b0 )
0(
0'
0&
0%
b0 $
0#
b0 "
0!
$end
#5000
1&
#10000
0&
#15000
1&
#20000
0&
1(
#25000
b10 *
1#
b1 +
1%
b10 $
b10 )
1&
#30000
0&
#35000
b1 -
1#
b1 +
0%
1&
#40000
0&
#45000
1!
0#
1&
#50000
0&
#55000
1!
1&
#60000
0&
#65000
1!
1&
#70000
0&
#75000
b11001100110011000011001100110011 "
b11001100110011000011001100110011 ,
1!
b10 +
1'
1&
#80000
0&
#85000
1!
b10 -
b0 +
0'
1&
#90000
0&
#95000
b0 -
0!
1&
#100000
0&
#105000
1#
1&
#110000
0&
#115000
1#
1&
#120000
0&
#125000
1#
1&
