AXI_ACE_COMB/ace_3state_fsm.v
module ace_3state_fsm (
    input        clk,
    input        rst_n,

    // ACE / AXI signals
    input        acvalid,
    input        awvalid,
    input        arvalid,
    input        crready,
    input        acsnoop,   // 1-bit (0 or 1)

    // State indicators
    output reg   invalid,
    output reg   unique_clean,
    output reg   unique_dirty,

    // Action signals
    output reg   write_main_mem,
    output reg   write_cache,
    output reg   read_main_mem,
    output reg   read_cache
);

    // ---------------------------
    // State encoding (Verilog)
    // ---------------------------
    localparam INVALID      = 2'd0;
    localparam UNIQUE_CLEAN = 2'd1;
    localparam UNIQUE_DIRTY = 2'd2;

    reg [1:0] state;
    reg [1:0] next_state;

    // ---------------------------
    // State register
    // ---------------------------
    always @(posedge clk or negedge rst_n) begin
        if (!rst_n)
            state <= INVALID;
        else
            state <= next_state;
    end

    // ---------------------------
    // Next-state logic
    // ---------------------------
    always @(*) begin
        next_state = state;

        case (state)

            INVALID: begin
                if (acvalid)
                    next_state = UNIQUE_DIRTY;
                else
                    next_state = INVALID;
            end

            UNIQUE_DIRTY: begin
                if (acsnoop == 1'b1)
                    next_state = UNIQUE_CLEAN;
                else if (!acvalid && !awvalid && !arvalid)
                    next_state = INVALID;
                else
                    next_state = UNIQUE_DIRTY;
                end


            UNIQUE_CLEAN: begin
                if (!acvalid && !awvalid && !arvalid)
                    next_state = INVALID;
                else
                    next_state = UNIQUE_CLEAN;
            end

            default: begin
                next_state = INVALID;
            end

        endcase
    end

    // ---------------------------
    // Output logic
    // ---------------------------
    always @(*) begin
        // Default outputs
        invalid        = 1'b0;
        unique_clean   = 1'b0;
        unique_dirty   = 1'b0;

        write_main_mem = 1'b0;
        write_cache    = 1'b0;
        read_main_mem  = 1'b0;
        read_cache     = 1'b0;

        case (state)

            INVALID: begin
                invalid = 1'b1;

                if (awvalid)
                    write_main_mem = 1'b1;

                if (arvalid)
                    read_main_mem = 1'b1;
            end

            UNIQUE_DIRTY: begin
                unique_dirty = 1'b1;

                // Write to main memory and cache
                if (awvalid && acvalid) begin
                    write_main_mem = 1'b1;
                    write_cache    = 1'b1;
                end

                // Read from main memory
                if (arvalid && crready)
                    read_main_mem = 1'b1;
            end

            UNIQUE_CLEAN: begin
                unique_clean = 1'b1;

                // Write to main memory and cache
                if (awvalid && acvalid) begin
                    write_main_mem = 1'b1;
                    write_cache    = 1'b1;
                end

                // Read from cache
                if (arvalid && crready)
                    read_cache = 1'b1;
            end

            default: begin
                // Do nothing
            end

        endcase
    end

endmodule

ace_main/ace_tb/tb_ace_3state_fsm.v
`timescale 1ns/1ps

module tb_ace_3state_fsm_fixed;

    reg clk;
    reg rst_n;

    reg acvalid;
    reg awvalid;
    reg arvalid;
    reg crready;
    reg acsnoop;

    wire invalid;
    wire unique_dirty;
    wire unique_clean;

    wire write_main_mem;
    wire write_cache;
    wire read_main_mem;
    wire read_cache;

    // DUT
    ace_3state_fsm dut (
        .clk(clk),
        .rst_n(rst_n),
        .acvalid(acvalid),
        .awvalid(awvalid),
        .arvalid(arvalid),
        .crready(crready),
        .acsnoop(acsnoop),
        .invalid(invalid),
        .unique_clean(unique_clean),
        .unique_dirty(unique_dirty),
        .write_main_mem(write_main_mem),
        .write_cache(write_cache),
        .read_main_mem(read_main_mem),
        .read_cache(read_cache)
    );

    // Clock
    always #5 clk = ~clk;

    initial begin
        $dumpfile("ace_fsm_fixed.vcd");
        $dumpvars(0, tb_ace_3state_fsm_fixed);

        // Init
        clk = 0;
        rst_n = 0;
        acvalid = 0;
        awvalid = 0;
        arvalid = 0;
        crready = 0;
        acsnoop = 0;

        // -------------------------
        // RESET → INVALID
        // -------------------------
        #20 rst_n = 1;
        #20;

        // =========================
        // INVALID operations
        // =========================
        arvalid = 1;
        #10;
        arvalid = 0;
        awvalid = 1;
        #10;
        awvalid = 0;
        #20;
    

        // =========================
        // INVALID → UNIQUE_DIRTY
        // =========================
        acvalid = 1;
        #10;
        awvalid = 1;
        #10;
        acvalid = 0;
        awvalid = 0;
        arvalid = 1;
        crready = 1;
        #10;

        acsnoop = 1;

        #20;

        acsnoop = 0;
        acvalid = 1;
        awvalid = 1;
        arvalid = 0;
        crready = 0;
        
        #20;



        $finish;
    end

    initial begin
        $monitor(
            "T=%0t | INV=%b UD=%b UC=%b | Wm=%b Wc=%b Rm=%b Rc=%b",
            $time,
            invalid,
            unique_dirty,
            unique_clean,
            write_main_mem,
            write_cache,
            read_main_mem,
            read_cache
        );
    end

endmodule

waveforms_ace/ace_fsm_fixed.vcd
$date
	Thu Jan 29 11:07:42 2026
$end
$version
	Icarus Verilog
$end
$timescale
	1ps
$end
$scope module tb_ace_3state_fsm_fixed $end
$var wire 1 ! write_main_mem $end
$var wire 1 " write_cache $end
$var wire 1 # unique_dirty $end
$var wire 1 $ unique_clean $end
$var wire 1 % read_main_mem $end
$var wire 1 & read_cache $end
$var wire 1 ' invalid $end
$var reg 1 ( acsnoop $end
$var reg 1 ) acvalid $end
$var reg 1 * arvalid $end
$var reg 1 + awvalid $end
$var reg 1 , clk $end
$var reg 1 - crready $end
$var reg 1 . rst_n $end
$scope module dut $end
$var wire 1 ( acsnoop $end
$var wire 1 ) acvalid $end
$var wire 1 * arvalid $end
$var wire 1 + awvalid $end
$var wire 1 , clk $end
$var wire 1 - crready $end
$var wire 1 . rst_n $end
$var reg 1 ' invalid $end
$var reg 2 / next_state [1:0] $end
$var reg 1 & read_cache $end
$var reg 1 % read_main_mem $end
$var reg 2 0 state [1:0] $end
$var reg 1 $ unique_clean $end
$var reg 1 # unique_dirty $end
$var reg 1 " write_cache $end
$var reg 1 ! write_main_mem $end
$upscope $end
$upscope $end
$enddefinitions $end
#0
$dumpvars
b0 0
b0 /
0.
0-
0,
0+
0*
0)
0(
1'
0&
0%
0$
0#
0"
0!
$end
#5000
1,
#10000
0,
#15000
1,
#20000
0,
1.
#25000
1,
#30000
0,
#35000
1,
#40000
1%
1'
0,
1*
#45000
1,
#50000
1!
0%
1'
0,
1+
0*
#55000
1,
#60000
0!
1'
0,
0+
#65000
1,
#70000
0,
#75000
1,
#80000
1'
b10 /
0,
1)
#85000
1#
0'
b10 0
1,
#90000
1"
1!
1#
0,
1+
#95000
1,
#100000
1%
0"
0!
1#
0,
1-
1*
0+
0)
#105000
1,
#110000
b1 /
0,
1(
#115000
1&
1$
0%
0#
b1 0
1,
#120000
0,
#125000
1,
#130000
1"
1!
0&
1$
0,
0-
0*
1+
1)
0(
