AXI_ACE_COMB/ace_3state_fsm.v
module ace_3state_fsm (
    input        clk,
    input        rst_n,

    // ACE / AXI signals
    input        acvalid,
    input        awvalid,
    input        arvalid,
    input        crready,
    input        acsnoop,   // 1-bit (0 or 1)

    // State indicators
    output reg   invalid,
    output reg   unique_clean,
    output reg   unique_dirty,

    // Action signals
    output reg   write_main_mem,
    output reg   write_cache,
    output reg   read_main_mem,
    output reg   read_cache
);

    // ---------------------------
    // State encoding (Verilog)
    // ---------------------------
    localparam INVALID      = 2'd0;
    localparam UNIQUE_CLEAN = 2'd1;
    localparam UNIQUE_DIRTY = 2'd2;

    reg [1:0] state;
    reg [1:0] next_state;

    // ---------------------------
    // State register
    // ---------------------------
    always @(posedge clk or negedge rst_n) begin
        if (!rst_n)
            state <= INVALID;
        else
            state <= next_state;
    end

    // ---------------------------
    // Next-state logic
    // ---------------------------
    always @(*) begin
        next_state = state;

        case (state)

            INVALID: begin
                if (acvalid)
                    next_state = UNIQUE_DIRTY;
                else
                    next_state = INVALID;
            end

            UNIQUE_DIRTY: begin
                if (acsnoop == 1'b1)
                    next_state = UNIQUE_CLEAN;
                else if (!acvalid && !awvalid && !arvalid)
                    next_state = INVALID;
                else
                    next_state = UNIQUE_DIRTY;
                end


            UNIQUE_CLEAN: begin
                if (!acvalid && !awvalid && !arvalid)
                    next_state = INVALID;
                else
                    next_state = UNIQUE_CLEAN;
            end

            default: begin
                next_state = INVALID;
            end

        endcase
    end

    // ---------------------------
    // Output logic
    // ---------------------------
    always @(*) begin
        // Default outputs
        invalid        = 1'b0;
        unique_clean   = 1'b0;
        unique_dirty   = 1'b0;

        write_main_mem = 1'b0;
        write_cache    = 1'b0;
        read_main_mem  = 1'b0;
        read_cache     = 1'b0;

        case (state)

            INVALID: begin
                invalid = 1'b1;

                if (awvalid)
                    write_main_mem = 1'b1;

                if (arvalid)
                    read_main_mem = 1'b1;
            end

            UNIQUE_DIRTY: begin
                unique_dirty = 1'b1;

                // Write to main memory and cache
                if (awvalid && acvalid) begin
                    write_main_mem = 1'b1;
                    write_cache    = 1'b1;
                end

                // Read from main memory
                if (arvalid && crready)
                    read_main_mem = 1'b1;
            end

            UNIQUE_CLEAN: begin
                unique_clean = 1'b1;

                // Write to main memory and cache
                if (awvalid && acvalid) begin
                    write_main_mem = 1'b1;
                    write_cache    = 1'b1;
                end

                // Read from cache
                if (arvalid && crready)
                    read_cache = 1'b1;
            end

            default: begin
                // Do nothing
            end

        endcase
    end

endmodule

ace_main/ace_tb/tb_invalid_state.v
`timescale 1ns/1ps

module tb_invalid_state;

    // Clock and reset
    reg clk;
    reg rst_n;

    // Inputs
    reg acvalid;
    reg awvalid;
    reg arvalid;
    reg crready;
    reg acsnoop;

    // Outputs
    wire invalid;
    wire unique_clean;
    wire unique_dirty;

    wire write_main_mem;
    wire write_cache;
    wire read_main_mem;
    wire read_cache;

    // -------------------------
    // DUT instantiation
    // -------------------------
    ace_3state_fsm dut (
        .clk(clk),
        .rst_n(rst_n),
        .acvalid(acvalid),
        .awvalid(awvalid),
        .arvalid(arvalid),
        .crready(crready),
        .acsnoop(acsnoop),
        .invalid(invalid),
        .unique_clean(unique_clean),
        .unique_dirty(unique_dirty),
        .write_main_mem(write_main_mem),
        .write_cache(write_cache),
        .read_main_mem(read_main_mem),
        .read_cache(read_cache)
    );

    // -------------------------
    // Clock generation
    // -------------------------
    always #5 clk = ~clk;

    // -------------------------
    // Test stimulus
    // -------------------------
    initial begin
        // Dump for GTKWave
        $dumpfile("invalid_state.vcd");
        $dumpvars(0, tb_invalid_state);

        // Init
        clk      = 0;
        rst_n    = 0;
        acvalid  = 0;
        awvalid  = 0;
        arvalid  = 0;
        crready  = 0;
        acsnoop  = 0;

        // Apply reset
        #20;
        rst_n = 1;

        // ---------------------------
        // 1. Stay in INVALID (idle)
        // ---------------------------
        #20;

        // ---------------------------
        // 2. Write in INVALID
        // ---------------------------
        awvalid = 1;
        #10;
        awvalid = 0;

        // ---------------------------
        // 3. Read in INVALID
        // ---------------------------
        arvalid = 1;
        #10;
        arvalid = 0;

        // ---------------------------
        // 4. Ensure no transition
        // ---------------------------
        #10;

        acvalid = 1;

        #10;

        acvalid = 0;
        awvalid = 0;
        arvalid = 0;

        #20;

        

        // End simulation
        $finish;
    end

    // -------------------------
    // Monitor
    // -------------------------
    initial begin
        $monitor(
            "T=%0t | INVALID=%b UC=%b UD=%b | Wm=%b Rm=%b",
            $time,
            invalid,
            unique_clean,
            unique_dirty,
            write_main_mem,
            read_main_mem
        );
    end

endmodule

waveforms_ace/invalid_state.vcd
$date
	Wed Jan 28 11:12:07 2026
$end
$version
	Icarus Verilog
$end
$timescale
	1ps
$end
$scope module tb_invalid_state $end
$var wire 1 ! write_main_mem $end
$var wire 1 " write_cache $end
$var wire 1 # unique_dirty $end
$var wire 1 $ unique_clean $end
$var wire 1 % read_main_mem $end
$var wire 1 & read_cache $end
$var wire 1 ' invalid $end
$var reg 1 ( acsnoop $end
$var reg 1 ) acvalid $end
$var reg 1 * arvalid $end
$var reg 1 + awvalid $end
$var reg 1 , clk $end
$var reg 1 - crready $end
$var reg 1 . rst_n $end
$scope module dut $end
$var wire 1 ( acsnoop $end
$var wire 1 ) acvalid $end
$var wire 1 * arvalid $end
$var wire 1 + awvalid $end
$var wire 1 , clk $end
$var wire 1 - crready $end
$var wire 1 . rst_n $end
$var reg 1 ' invalid $end
$var reg 2 / next_state [1:0] $end
$var reg 1 & read_cache $end
$var reg 1 % read_main_mem $end
$var reg 2 0 state [1:0] $end
$var reg 1 $ unique_clean $end
$var reg 1 # unique_dirty $end
$var reg 1 " write_cache $end
$var reg 1 ! write_main_mem $end
$upscope $end
$upscope $end
$enddefinitions $end
#0
$dumpvars
b0 0
b0 /
0.
0-
0,
0+
0*
0)
0(
1'
0&
0%
0$
0#
0"
0!
$end
#5000
1,
#10000
0,
#15000
1,
#20000
0,
1.
#25000
1,
#30000
0,
#35000
1,
#40000
1!
1'
0,
1+
#45000
1,
#50000
1%
0!
1'
0,
1*
0+
#55000
1,
#60000
0%
1'
0,
0*
#65000
1,
#70000
1'
b10 /
0,
1)
#75000
1#
0'
b0 /
b10 0
1,
#80000
1#
b0 /
0,
0)
#85000
1'
0#
b0 0
1,
